chasten/__init__.py
chasten/__main__.py
chasten/checks.py
chasten/configApp.py
chasten/configuration.py
chasten/constants.py
chasten/createchecks.py
chasten/database.py
chasten/debug.py
chasten/enumerations.py
chasten/filesystem.py
chasten/main.py
chasten/output.py
chasten/process.py
chasten/results.py
chasten/server.py
chasten/util.py
chasten/validate.py
chasten-1.0.0.dist-info/LICENSE
chasten-1.0.0.dist-info/METADATA
chasten-1.0.0.dist-info/WHEEL
chasten-1.0.0.dist-info/entry_points.txt
chasten-1.0.0.dist-info/RECORD
