Metadata-Version: 2.1
Name: chasten
Version: 1.0.0
Summary: Chasten checks the AST of a Python program!
Author: Gregory M. Kapfhammer
Author-email: gkapfham@allegheny.edu
Requires-Python: >=3.11,<4.0
Classifier: Programming Language :: Python :: 3
Classifier: Programming Language :: Python :: 3.11
Classifier: Programming Language :: Python :: 3.12
Requires-Dist: cryptography (>=41.0.5,<42.0.0)
Requires-Dist: datasette (>=0.64.3,<0.65.0)
Requires-Dist: datasette-copyable (>=0.3.2,<0.4.0)
Requires-Dist: datasette-export-notebook (>=1.0,<2.0)
Requires-Dist: datasette-publish-fly (>=1.3,<2.0)
Requires-Dist: datasette-publish-vercel (>=0.14.2,<0.15.0)
Requires-Dist: datasette-search-all (>=1.1.1,<2.0.0)
Requires-Dist: datasette-sqlite-regex (>=0.2.3,<0.3.0)
Requires-Dist: flatterer (>=0.19.8,<0.20.0)
Requires-Dist: frogmouth (>=0.9.0,<0.10.0)
Requires-Dist: jsonschema (>=4.18.3,<5.0.0)
Requires-Dist: numpy (>=1.25.2,<2.0.0)
Requires-Dist: openai (>=0.28.1,<0.29.0)
Requires-Dist: platformdirs (>=3.8.1,<4.0.0)
Requires-Dist: pyastgrep (>=1.2.2,<2.0.0)
Requires-Dist: pydantic (>=2.0.3,<3.0.0)
Requires-Dist: python-levenshtein (>=0.21.1,<0.22.0)
Requires-Dist: pyyaml (>=6.0,<7.0)
Requires-Dist: requests (>=2.31.0,<3.0.0)
Requires-Dist: rich (>=13.4.2,<14.0.0)
Requires-Dist: sqlean-py (>=0.21.5.3,<0.22.0.0)
Requires-Dist: sqlite-regex (>=0.2.3,<0.3.0)
Requires-Dist: sqlite-utils (>=3.34,<4.0)
Requires-Dist: textual (>=0.41.0,<0.42.0)
Requires-Dist: thefuzz (>=0.19.0,<0.20.0)
Requires-Dist: trogon (>=0.5.0,<0.6.0)
Requires-Dist: typer[all] (>=0.9.0,<0.10.0)
Requires-Dist: urllib3 (>=2.0.7,<3.0.0)
